django_metaauth-0.1.2.dist-info/licenses/LICENSE
metaauth/__init__.py
metaauth/admin.py
metaauth/apps.py
metaauth/models.py
metaauth/settings.py
metaauth/tests.py
metaauth/urls.py
metaauth/views.py
metaauth/migrations/0001_initial.py
metaauth/migrations/0002_alter_token_external_id_alter_token_token.py
metaauth/migrations/__init__.py
metaauth/templates/metaauth/error.html
metaauth/templates/metaauth/success.html
tests/__init__.py
tests/test_models.py
tests/test_settings.py
tests/test_settings_module.py
tests/test_views.py
tests/urls.py
django_metaauth-0.1.2.dist-info/METADATA
django_metaauth-0.1.2.dist-info/WHEEL
django_metaauth-0.1.2.dist-info/top_level.txt
django_metaauth-0.1.2.dist-info/RECORD
